renkuaqsannotation/__init__.py
renkuaqsannotation/config.py
renkuaqsannotation/graph_utils.py
renkuaqsannotation/io_utils.py
renkuaqsannotation/oda_annotation.py
renkuaqsannotation/plugin.py
renku_aqs_annotation-0.0.4.dist-info/LICENSE
renku_aqs_annotation-0.0.4.dist-info/METADATA
renku_aqs_annotation-0.0.4.dist-info/WHEEL
renku_aqs_annotation-0.0.4.dist-info/entry_points.txt
renku_aqs_annotation-0.0.4.dist-info/top_level.txt
renku_aqs_annotation-0.0.4.dist-info/RECORD
