Metadata-Version: 2.1
Name: renku-aqs-annotation
Version: 0.0.4
Summary: Renku AQS annotation plugin
Author: Gabriele Barni, Volodymyr Savchenko
Author-email: 
License: Apache License 2.0
Keywords: Renku AQS annotation
Platform: any
Classifier: Environment :: Web Environment
Classifier: Intended Audience :: Developers
Classifier: Intended Audience :: Science/Research
Classifier: License :: OSI Approved :: Apache Software License
Classifier: Operating System :: OS Independent
Classifier: Programming Language :: Python
Classifier: Topic :: Internet :: WWW/HTTP :: Dynamic Content
Classifier: Topic :: Software Development :: Libraries :: Python Modules
Classifier: Programming Language :: Python :: 3
Classifier: Programming Language :: Python :: 3.5
Classifier: Programming Language :: Python :: 3.6
Classifier: Programming Language :: Python :: 3.7
Classifier: Programming Language :: Python :: 3.8
Classifier: Development Status :: 4 - Beta
Requires-Python: >=3.9,<3.12
License-File: LICENSE
Requires-Dist: deepdiff
Requires-Dist: pydotplus
Requires-Dist: bs4
Requires-Dist: renku <3,>=2.7
Requires-Dist: matplotlib
Requires-Dist: astroquery
Requires-Dist: aqsconverters
Requires-Dist: nb2workflow[rdf] >=1.3.41
Requires-Dist: pyvis ==0.3.0
Requires-Dist: lockfile
Requires-Dist: pytest
